README.md
setup.cfg
setup.py
yamlval/BaseType.py
yamlval/BoundedType.py
yamlval/MultiType.py
yamlval/__init__.py
yamlval/example.py
yamlval/yAny.py
yamlval/yDict.py
yamlval/yEnum.py
yamlval/yFloat.py
yamlval/yInt.py
yamlval/yList.py
yamlval/yNone.py
yamlval/ySchema.py
yamlval/yString.py
yamlval.egg-info/PKG-INFO
yamlval.egg-info/SOURCES.txt
yamlval.egg-info/dependency_links.txt
yamlval.egg-info/requires.txt
yamlval.egg-info/top_level.txt