Metadata-Version: 2.1
Name: yamlval
Version: 1.0.2
Summary: A YAML type validator
Home-page: https://github.com/mycicle/yamlval/
Author: Michael DiGregorio
Author-email: mjm.digregorio@gmail.com
License: UNKNOWN
Download-URL: https://github.com/mycicle/yamlval/archive/v1.0.2.tar.gz
Platform: UNKNOWN
Classifier: Intended Audience :: Developers
Classifier: Programming Language :: Python :: 3.6
Classifier: Programming Language :: Python :: 3.7
Classifier: Programming Language :: Python :: 3.8
Classifier: License :: OSI Approved :: MIT License
